{
  "anonymous": false,
  "attributes": [
    {
      "name": "Datastore Configuration",
      "values": [
        "[{\"data\":\"Template Name\",\"title\":\"Template Name\",\"visible\":true,\"searchable\":true,\"orderable\":true},{\"data\":\"Template Description\",\"title\":\"Template Description\",\"visible\":true,\"searchable\":true,\"orderable\":true},{\"data\":\"Template Parameters\",\"title\":\"Template Parameters\",\"visible\":false,\"searchable\":false,\"orderable\":false},{\"data\":\"Status\",\"title\":\"Status\",\"visible\":true,\"searchable\":true,\"orderable\":true}]"
      ]
    }
  ],
  "bridgedResources": [

  ],
  "categorizations": [

  ],
  "createdAt": "2016-04-28T22:16:26.312Z",
  "createdBy": "james.davies@kineticdata.com",
  "description": "Amazon Cloud Formation Templates",
  "name": "AWS Cloud Formation Templates",
  "notes": null,
  "pages": [
    {
      "advanceCondition": "false",
      "displayCondition": null,
      "displayPage": "pages/datastore/datastoreForm.jsp",
      "elements": [
        {
          "type": "field",
          "name": "Template Name",
          "label": "Template Name",
          "key": "f2",
          "defaultValue": null,
          "defaultResourceName": null,
          "visible": true,
          "enabled": true,
          "required": true,
          "requiredMessage": null,
          "omitWhenHidden": null,
          "pattern": null,
          "constraints": [

          ],
          "events": [

          ],
          "renderAttributes": {

          },
          "dataType": "string",
          "renderType": "text",
          "rows": 1
        },
        {
          "type": "field",
          "name": "Template Description",
          "label": "Template Description",
          "key": "f3",
          "defaultValue": null,
          "defaultResourceName": null,
          "visible": true,
          "enabled": true,
          "required": false,
          "requiredMessage": null,
          "omitWhenHidden": null,
          "pattern": null,
          "constraints": [

          ],
          "events": [

          ],
          "renderAttributes": {

          },
          "dataType": "string",
          "renderType": "text",
          "rows": 1
        },
        {
          "type": "field",
          "name": "Template Parameters",
          "label": "Template Parameters",
          "key": "f4",
          "defaultValue": null,
          "defaultResourceName": null,
          "visible": true,
          "enabled": true,
          "required": true,
          "requiredMessage": null,
          "omitWhenHidden": null,
          "pattern": null,
          "constraints": [

          ],
          "events": [

          ],
          "renderAttributes": {

          },
          "dataType": "string",
          "renderType": "text",
          "rows": 6
        },
        {
          "type": "field",
          "name": "Template Url",
          "label": "Template Url",
          "key": "f5",
          "defaultValue": null,
          "defaultResourceName": null,
          "visible": true,
          "enabled": true,
          "required": false,
          "requiredMessage": null,
          "omitWhenHidden": null,
          "pattern": null,
          "constraints": [

          ],
          "events": [

          ],
          "renderAttributes": {

          },
          "dataType": "string",
          "renderType": "text",
          "rows": 1
        },
        {
          "type": "field",
          "name": "Status",
          "label": "Status",
          "key": "f1",
          "defaultValue": null,
          "defaultResourceName": null,
          "visible": true,
          "enabled": true,
          "required": true,
          "requiredMessage": null,
          "omitWhenHidden": null,
          "pattern": null,
          "constraints": [

          ],
          "events": [

          ],
          "renderAttributes": {

          },
          "dataType": "string",
          "renderType": "radio",
          "choicesResourceName": null,
          "choicesRunIf": null,
          "choices": [
            {
              "label": "Active",
              "value": "active"
            },
            {
              "label": "Inactive",
              "value": "inactive"
            }
          ]
        },
        {
          "type": "button",
          "label": "Save",
          "name": "Save",
          "visible": "bundle.adminDatastore != null",
          "enabled": true,
          "renderType": "submit-page",
          "renderAttributes": {
            "class": "btn btn-primary"
          }
        },
        {
          "type": "button",
          "label": "Cancel",
          "name": "Cancel",
          "visible": "bundle.adminDatastore != null",
          "enabled": true,
          "renderType": "custom",
          "renderAttributes": {
            "class": "btn btn-link cancel-record"
          },
          "events": [

          ]
        }
      ],
      "events": [

      ],
      "name": "Datastore",
      "renderType": "submittable",
      "type": "page"
    }
  ],
  "securityPolicies": [

  ],
  "slug": "aws-cloud-formation-templates",
  "status": "Active",
  "submissionLabelExpression": null,
  "type": "Datastore",
  "updatedAt": "2016-05-02T17:59:28.236Z",
  "updatedBy": "james.davies@kineticdata.com"
}