{
  "anonymous": false,
  "attributes": [
    {
      "name": "Kapp Slug",
      "values": [
        "ticket"
      ]
    }
  ],
  "bridgedResources": [

  ],
  "categorizations": [

  ],
  "createdAt": "2016-04-14T16:26:28.722Z",
  "createdBy": "marcin.zarycki@kineticdata.com",
  "description": "Allows for creating and management of groups and their members.",
  "name": "Group Management",
  "notes": null,
  "pages": [
    {
      "advanceCondition": null,
      "displayCondition": null,
      "displayPage": "pages/groups/console.jsp",
      "elements": [

      ],
      "events": [

      ],
      "name": "Group Management",
      "renderType": "submittable",
      "type": "page"
    }
  ],
  "securityPolicies": [

  ],
  "slug": "group-management",
  "status": "New",
  "submissionLabelExpression": null,
  "type": "Console",
  "updatedAt": "2016-06-03T20:06:37.489Z",
  "updatedBy": "james.davies@kineticdata.com"
}