{
  "anonymous": false,
  "attributes": [
    {
      "name": "Approval Form Slug",
      "values": [
        "approval"
      ]
    },
    {
      "name": "Fulfillment Form Slug",
      "values": [
        "hr-fulfillment"
      ]
    },
    {
      "name": "Fulfillment Group",
      "values": [
        "Fulfillment::Human Resources"
      ]
    },
    {
      "name": "Image",
      "values": [
        "401k-request.png"
      ]
    },
    {
      "name": "SLA",
      "values": [
        "2 Days"
      ]
    }
  ],
  "bridgedResources": [

  ],
  "categorizations": [
    {
      "category": {
        "name": "HR Services",
        "slug": "hr-services"
      }
    }
  ],
  "createdAt": "2016-02-16T16:24:37.109Z",
  "createdBy": "user@kineticdata.com",
  "description": "Use this form to request an increase or decrease in the percentage or your salary that is regularly contributed to your 401k.",
  "name": "401k Increase Request",
  "notes": "a",
  "pages": [
    {
      "advanceCondition": null,
      "displayCondition": null,
      "displayPage": null,
      "elements": [
        {
          "type": "field",
          "name": "Increase or Decrease",
          "label": "Increase or Decrease",
          "key": "f1",
          "defaultValue": null,
          "defaultResourceName": null,
          "visible": true,
          "enabled": true,
          "required": true,
          "requiredMessage": null,
          "pattern": null,
          "constraints": [

          ],
          "events": [

          ],
          "renderAttributes": {

          },
          "dataType": "string",
          "renderType": "dropdown",
          "choicesResourceName": null,
          "choices": [
            {
              "label": "Increase",
              "value": "Increase"
            },
            {
              "label": "Decrease",
              "value": "Decrease"
            }
          ],
          "choicesRunIf": null,
          "omitWhenHidden": null
        },
        {
          "type": "field",
          "name": "Amount",
          "label": "Amount (US Dollars)",
          "key": "f3",
          "defaultValue": null,
          "defaultResourceName": null,
          "visible": true,
          "enabled": true,
          "required": true,
          "requiredMessage": null,
          "omitWhenHidden": null,
          "pattern": {
            "regex": "\"^\\$?\\-?([1-9]{1}[0-9]{0,2}(\\,\\d{3})*(\\.\\d{0,2})?|[1-9]{1}\\d{0,}(\\.\\d{0,2})?|0(\\.\\d{0,2})?|(\\.\\d{1,2}))$|^\\-?\\$?([1-9]{1}\\d{0,2}(\\,\\d{3})*(\\.\\d{0,2})?|[1-9]{1}\\d{0,}(\\.\\d{0,2})?|0(\\.\\d{0,2})?|(\\.\\d{1,2}))$|^\\(\\$?([1-9]{1}\\d{0,2}(\\,\\d{3})*(\\.\\d{0,2})?|[1-9]{1}\\d{0,}(\\.\\d{0,2})?|0(\\.\\d{0,2})?|(\\.\\d{1,2}))\\)$\"",
            "message": "Please Enter Valid US Dollar Amount"
          },
          "constraints": [

          ],
          "events": [

          ],
          "renderAttributes": {
            "placeholder": "$100.00"
          },
          "dataType": "string",
          "renderType": "text",
          "rows": 1
        },
        {
          "type": "field",
          "name": "Why do you need this 401k Adjustment",
          "label": "Why do you need this 401k Adjustment",
          "key": "f2",
          "defaultValue": null,
          "defaultResourceName": null,
          "visible": true,
          "enabled": true,
          "required": false,
          "requiredMessage": null,
          "pattern": null,
          "constraints": [

          ],
          "events": [

          ],
          "renderAttributes": {

          },
          "dataType": "string",
          "renderType": "text",
          "rows": 3,
          "omitWhenHidden": null
        },
        {
          "type": "button",
          "label": "Submit",
          "name": "Submit Button",
          "visible": true,
          "enabled": true,
          "renderType": "submit-page",
          "renderAttributes": {

          }
        }
      ],
      "events": [

      ],
      "name": "Page 1",
      "renderType": "submittable",
      "type": "page"
    }
  ],
  "securityPolicies": [

  ],
  "slug": "401k-increase-request",
  "status": "Active",
  "submissionLabelExpression": "${values('Increase or Decrease')} - ${values('Amount')}",
  "type": "Service",
  "updatedAt": "2016-06-06T23:09:46.395Z",
  "updatedBy": "demo.taskman@kineticdata.com"
}